leafmap/__init__.py
leafmap/__main__.py
leafmap/basemaps.py
leafmap/bokehmap.py
leafmap/cli.py
leafmap/colormaps.py
leafmap/common.py
leafmap/deck.py
leafmap/deckgl.py
leafmap/download.py
leafmap/foliumap.py
leafmap/heremap.py
leafmap/kepler.py
leafmap/leafmap.py
leafmap/legends.py
leafmap/map_widgets.py
leafmap/mapbox.py
leafmap/maplibregl.py
leafmap/osm.py
leafmap/pc.py
leafmap/plot.py
leafmap/plotlymap.py
leafmap/report.py
leafmap/stac.py
leafmap/toolbar.py
leafmap/data/census_data.json
leafmap/data/pc_inventory.json
leafmap/data/fonts/arial.ttf
leafmap/data/template/legend.html
leafmap/data/template/legend.txt
leafmap/data/template/legend_style.html
leafmap/examples/__init__.py
leafmap/examples/datasets.txt
leafmap/javascript/mapbox.js
leafmap/styles/mapbox.css
leafmap-0.57.8.dist-info/licenses/LICENSE
leafmap-0.57.8.dist-info/METADATA
leafmap-0.57.8.dist-info/WHEEL
leafmap-0.57.8.dist-info/entry_points.txt
leafmap-0.57.8.dist-info/top_level.txt
leafmap-0.57.8.dist-info/RECORD
