Metadata-Version: 2.4
Name: leafmap
Version: 0.57.8
Summary: A Python package for geospatial analysis and interactive mapping in a Jupyter environment.
Author-email: Qiusheng Wu <giswqs@gmail.com>
License: MIT license
Project-URL: Homepage, https://github.com/opengeos/leafmap
Keywords: leafmap
Classifier: Development Status :: 2 - Pre-Alpha
Classifier: Intended Audience :: Developers
Classifier: License :: OSI Approved :: MIT License
Classifier: Natural Language :: English
Classifier: Programming Language :: Python :: 3
Classifier: Programming Language :: Python :: 3.9
Classifier: Programming Language :: Python :: 3.10
Classifier: Programming Language :: Python :: 3.11
Classifier: Programming Language :: Python :: 3.12
Classifier: Programming Language :: Python :: 3.13
Requires-Python: >=3.9
License-File: LICENSE
Requires-Dist: anywidget
Requires-Dist: bqplot
Requires-Dist: duckdb>=1.4.1
Requires-Dist: folium
Requires-Dist: gdown
Requires-Dist: geojson
Requires-Dist: geopandas
Requires-Dist: ipyevents
Requires-Dist: ipyfilechooser
Requires-Dist: ipyleaflet
Requires-Dist: ipyvuetify
Requires-Dist: ipywidgets
Requires-Dist: maplibre
Requires-Dist: matplotlib
Requires-Dist: numpy
Requires-Dist: pandas
Requires-Dist: plotly
Requires-Dist: pystac-client
Requires-Dist: python-box
Requires-Dist: scooby
Requires-Dist: whiteboxgui
Requires-Dist: xyzservices
Provides-Extra: backends
Requires-Dist: bokeh; extra == "backends"
Requires-Dist: keplergl; extra == "backends"
Requires-Dist: maplibre; extra == "backends"
Requires-Dist: pydeck; extra == "backends"
Requires-Dist: plotly; extra == "backends"
Provides-Extra: lidar
Requires-Dist: geopandas; extra == "lidar"
Requires-Dist: ipygany; extra == "lidar"
Requires-Dist: ipyvtklink; extra == "lidar"
Requires-Dist: laspy; extra == "lidar"
Requires-Dist: panel; extra == "lidar"
Requires-Dist: pyntcloud[LAS]; extra == "lidar"
Requires-Dist: pyvista[all]; extra == "lidar"
Provides-Extra: raster
Requires-Dist: localtileserver>=0.10.6; extra == "raster"
Requires-Dist: jupyter-server-proxy; extra == "raster"
Requires-Dist: rio-cogeo; extra == "raster"
Requires-Dist: rioxarray; extra == "raster"
Requires-Dist: netcdf4; extra == "raster"
Requires-Dist: d2spy; extra == "raster"
Requires-Dist: h5netcdf; extra == "raster"
Requires-Dist: h5py; extra == "raster"
Requires-Dist: opera-utils; extra == "raster"
Requires-Dist: psutil; extra == "raster"
Requires-Dist: titiler; extra == "raster"
Requires-Dist: uvicorn; extra == "raster"
Provides-Extra: viewer
Requires-Dist: localtileserver; extra == "viewer"
Requires-Dist: fiona; extra == "viewer"
Provides-Extra: usgs
Requires-Dist: pynhd; extra == "usgs"
Requires-Dist: py3dep; extra == "usgs"
Provides-Extra: sql
Requires-Dist: psycopg2; extra == "sql"
Requires-Dist: sqlalchemy; extra == "sql"
Provides-Extra: apps
Requires-Dist: streamlit-folium; extra == "apps"
Requires-Dist: voila; extra == "apps"
Requires-Dist: solara; extra == "apps"
Provides-Extra: vector
Requires-Dist: geopandas; extra == "vector"
Requires-Dist: osmnx; extra == "vector"
Requires-Dist: pmtiles; extra == "vector"
Requires-Dist: flask; extra == "vector"
Requires-Dist: flask-cors; extra == "vector"
Requires-Dist: lonboard; extra == "vector"
Requires-Dist: mapclassify; extra == "vector"
Requires-Dist: fiona; extra == "vector"
Provides-Extra: pmtiles
Requires-Dist: pmtiles; extra == "pmtiles"
Requires-Dist: flask; extra == "pmtiles"
Requires-Dist: flask-cors; extra == "pmtiles"
Provides-Extra: ai
Requires-Dist: geopandas; extra == "ai"
Requires-Dist: osmnx; extra == "ai"
Requires-Dist: localtileserver>=0.10.4; extra == "ai"
Requires-Dist: rastervision; extra == "ai"
Requires-Dist: pytorch-lightning; extra == "ai"
Requires-Dist: torchgeo; extra == "ai"
Provides-Extra: maplibre
Requires-Dist: anywidget; extra == "maplibre"
Requires-Dist: geopandas; extra == "maplibre"
Requires-Dist: fiona; extra == "maplibre"
Requires-Dist: h3; extra == "maplibre"
Requires-Dist: ipyvuetify; extra == "maplibre"
Requires-Dist: localtileserver; extra == "maplibre"
Requires-Dist: mapclassify; extra == "maplibre"
Requires-Dist: maplibre>=0.3.1; extra == "maplibre"
Requires-Dist: pmtiles; extra == "maplibre"
Requires-Dist: rioxarray; extra == "maplibre"
Requires-Dist: xarray; extra == "maplibre"
Provides-Extra: gdal
Requires-Dist: gdal; extra == "gdal"
Requires-Dist: pyproj; extra == "gdal"
Provides-Extra: duckdb
Requires-Dist: duckdb; extra == "duckdb"
Requires-Dist: duckdb-engine; extra == "duckdb"
Requires-Dist: jupysql; extra == "duckdb"
Requires-Dist: flask; extra == "duckdb"
Requires-Dist: flask-cors; extra == "duckdb"
Requires-Dist: jupyter-server-proxy; extra == "duckdb"
Provides-Extra: titiler
Requires-Dist: titiler; extra == "titiler"
Requires-Dist: uvicorn; extra == "titiler"
Dynamic: license-file
